txdir.py
txdir-2.0.2.data/data/man/man1/txdir.1
txdir-2.0.2.dist-info/LICENSE.txt
txdir-2.0.2.dist-info/METADATA
txdir-2.0.2.dist-info/WHEEL
txdir-2.0.2.dist-info/entry_points.txt
txdir-2.0.2.dist-info/top_level.txt
txdir-2.0.2.dist-info/RECORD
