Metadata-Version: 2.1
Name: txdir
Version: 2.0.2
Summary: Creating file tree from text tree and vice versa
Home-page: https://github.com/rpuntaie/txdir
Author: Roland Puntaier
Author-email: roland.puntaier@gmail.com
License: MIT
Keywords: text tree directory file content template
Classifier: Development Status :: 4 - Beta
Classifier: Intended Audience :: Developers
Classifier: Intended Audience :: System Administrators
Classifier: Intended Audience :: End Users/Desktop
Classifier: Operating System :: OS Independent
Classifier: Programming Language :: Python
Classifier: Programming Language :: Python :: 3
Classifier: License :: OSI Approved :: MIT License
Classifier: Environment :: Console
Classifier: Topic :: Software Development :: Libraries :: Python Modules
Classifier: Topic :: Desktop Environment :: File Managers
Classifier: Topic :: System :: Filesystems
Classifier: Topic :: Utilities
Requires-Python: >=3.6
License-File: LICENSE.txt
Requires-Dist: pathspec
